{"nodes": [{"id": "d_github_futuapi4go_pkg_constant_validation_test_go", "label": "validation_test.go", "file_type": "code", "source_file": "D:\\github\\futuapi4go\\pkg\\constant\\validation_test.go", "source_location": "L1"}, {"id": "constant_validation_test_testlotsize", "label": "TestLotSize()", "file_type": "code", "source_file": "D:\\github\\futuapi4go\\pkg\\constant\\validation_test.go", "source_location": "L5"}, {"id": "constant_validation_test_testpricetick", "label": "TestPriceTick()", "file_type": "code", "source_file": "D:\\github\\futuapi4go\\pkg\\constant\\validation_test.go", "source_location": "L32"}, {"id": "constant_validation_test_testvalidateaccid", "label": "TestValidateAccID()", "file_type": "code", "source_file": "D:\\github\\futuapi4go\\pkg\\constant\\validation_test.go", "source_location": "L54"}, {"id": "constant_validation_test_testvalidatecode", "label": "TestValidateCode()", "file_type": "code", "source_file": "D:\\github\\futuapi4go\\pkg\\constant\\validation_test.go", "source_location": "L63"}, {"id": "constant_validation_test_testvalidateqty", "label": "TestValidateQty()", "file_type": "code", "source_file": "D:\\github\\futuapi4go\\pkg\\constant\\validation_test.go", "source_location": "L76"}, {"id": "constant_validation_test_testvalidateprice", "label": "TestValidatePrice()", "file_type": "code", "source_file": "D:\\github\\futuapi4go\\pkg\\constant\\validation_test.go", "source_location": "L91"}, {"id": "constant_validation_test_testvalidateremark", "label": "TestValidateRemark()", "file_type": "code", "source_file": "D:\\github\\futuapi4go\\pkg\\constant\\validation_test.go", "source_location": "L106"}], "edges": [{"source": "d_github_futuapi4go_pkg_constant_validation_test_go", "target": "go_pkg_testing", "relation": "imports_from", "confidence": "EXTRACTED", "source_file": "D:\\github\\futuapi4go\\pkg\\constant\\validation_test.go", "source_location": "L3", "weight": 1.0, "context": "import"}, {"source": "d_github_futuapi4go_pkg_constant_validation_test_go", "target": "constant_validation_test_testlotsize", "relation": "contains", "confidence": "EXTRACTED", "source_file": "D:\\github\\futuapi4go\\pkg\\constant\\validation_test.go", "source_location": "L5", "weight": 1.0}, {"source": "d_github_futuapi4go_pkg_constant_validation_test_go", "target": "constant_validation_test_testpricetick", "relation": "contains", "confidence": "EXTRACTED", "source_file": "D:\\github\\futuapi4go\\pkg\\constant\\validation_test.go", "source_location": "L32", "weight": 1.0}, {"source": "d_github_futuapi4go_pkg_constant_validation_test_go", "target": "constant_validation_test_testvalidateaccid", "relation": "contains", "confidence": "EXTRACTED", "source_file": "D:\\github\\futuapi4go\\pkg\\constant\\validation_test.go", "source_location": "L54", "weight": 1.0}, {"source": "d_github_futuapi4go_pkg_constant_validation_test_go", "target": "constant_validation_test_testvalidatecode", "relation": "contains", "confidence": "EXTRACTED", "source_file": "D:\\github\\futuapi4go\\pkg\\constant\\validation_test.go", "source_location": "L63", "weight": 1.0}, {"source": "d_github_futuapi4go_pkg_constant_validation_test_go", "target": "constant_validation_test_testvalidateqty", "relation": "contains", "confidence": "EXTRACTED", "source_file": "D:\\github\\futuapi4go\\pkg\\constant\\validation_test.go", "source_location": "L76", "weight": 1.0}, {"source": "d_github_futuapi4go_pkg_constant_validation_test_go", "target": "constant_validation_test_testvalidateprice", "relation": "contains", "confidence": "EXTRACTED", "source_file": "D:\\github\\futuapi4go\\pkg\\constant\\validation_test.go", "source_location": "L91", "weight": 1.0}, {"source": "d_github_futuapi4go_pkg_constant_validation_test_go", "target": "constant_validation_test_testvalidateremark", "relation": "contains", "confidence": "EXTRACTED", "source_file": "D:\\github\\futuapi4go\\pkg\\constant\\validation_test.go", "source_location": "L106", "weight": 1.0}], "raw_calls": [{"caller_nid": "constant_validation_test_testlotsize", "callee": "TrdMarket", "is_member_call": false, "source_file": "D:\\github\\futuapi4go\\pkg\\constant\\validation_test.go", "source_location": "L16"}, {"caller_nid": "constant_validation_test_testlotsize", "callee": "Run", "is_member_call": true, "source_file": "D:\\github\\futuapi4go\\pkg\\constant\\validation_test.go", "source_location": "L20"}, {"caller_nid": "constant_validation_test_testlotsize", "callee": "LotSize", "is_member_call": false, "source_file": "D:\\github\\futuapi4go\\pkg\\constant\\validation_test.go", "source_location": "L21"}, {"caller_nid": "constant_validation_test_testlotsize", "callee": "Errorf", "is_member_call": true, "source_file": "D:\\github\\futuapi4go\\pkg\\constant\\validation_test.go", "source_location": "L23"}, {"caller_nid": "constant_validation_test_testlotsize", "callee": "Errorf", "is_member_call": true, "source_file": "D:\\github\\futuapi4go\\pkg\\constant\\validation_test.go", "source_location": "L26"}, {"caller_nid": "constant_validation_test_testpricetick", "callee": "TrdMarket", "is_member_call": false, "source_file": "D:\\github\\futuapi4go\\pkg\\constant\\validation_test.go", "source_location": "L42"}, {"caller_nid": "constant_validation_test_testpricetick", "callee": "Run", "is_member_call": true, "source_file": "D:\\github\\futuapi4go\\pkg\\constant\\validation_test.go", "source_location": "L46"}, {"caller_nid": "constant_validation_test_testpricetick", "callee": "PriceTick", "is_member_call": false, "source_file": "D:\\github\\futuapi4go\\pkg\\constant\\validation_test.go", "source_location": "L47"}, {"caller_nid": "constant_validation_test_testpricetick", "callee": "Errorf", "is_member_call": true, "source_file": "D:\\github\\futuapi4go\\pkg\\constant\\validation_test.go", "source_location": "L48"}, {"caller_nid": "constant_validation_test_testvalidateaccid", "callee": "ValidateAccID", "is_member_call": false, "source_file": "D:\\github\\futuapi4go\\pkg\\constant\\validation_test.go", "source_location": "L55"}, {"caller_nid": "constant_validation_test_testvalidateaccid", "callee": "Error", "is_member_call": true, "source_file": "D:\\github\\futuapi4go\\pkg\\constant\\validation_test.go", "source_location": "L56"}, {"caller_nid": "constant_validation_test_testvalidateaccid", "callee": "ValidateAccID", "is_member_call": false, "source_file": "D:\\github\\futuapi4go\\pkg\\constant\\validation_test.go", "source_location": "L58"}, {"caller_nid": "constant_validation_test_testvalidateaccid", "callee": "Errorf", "is_member_call": true, "source_file": "D:\\github\\futuapi4go\\pkg\\constant\\validation_test.go", "source_location": "L59"}, {"caller_nid": "constant_validation_test_testvalidatecode", "callee": "ValidateCode", "is_member_call": false, "source_file": "D:\\github\\futuapi4go\\pkg\\constant\\validation_test.go", "source_location": "L64"}, {"caller_nid": "constant_validation_test_testvalidatecode", "callee": "Error", "is_member_call": true, "source_file": "D:\\github\\futuapi4go\\pkg\\constant\\validation_test.go", "source_location": "L65"}, {"caller_nid": "constant_validation_test_testvalidatecode", "callee": "ValidateCode", "is_member_call": false, "source_file": "D:\\github\\futuapi4go\\pkg\\constant\\validation_test.go", "source_location": "L67"}, {"caller_nid": "constant_validation_test_testvalidatecode", "callee": "Errorf", "is_member_call": true, "source_file": "D:\\github\\futuapi4go\\pkg\\constant\\validation_test.go", "source_location": "L68"}, {"caller_nid": "constant_validation_test_testvalidatecode", "callee": "string", "is_member_call": false, "source_file": "D:\\github\\futuapi4go\\pkg\\constant\\validation_test.go", "source_location": "L70"}, {"caller_nid": "constant_validation_test_testvalidatecode", "callee": "make", "is_member_call": false, "source_file": "D:\\github\\futuapi4go\\pkg\\constant\\validation_test.go", "source_location": "L70"}, {"caller_nid": "constant_validation_test_testvalidatecode", "callee": "ValidateCode", "is_member_call": false, "source_file": "D:\\github\\futuapi4go\\pkg\\constant\\validation_test.go", "source_location": "L71"}, {"caller_nid": "constant_validation_test_testvalidatecode", "callee": "Error", "is_member_call": true, "source_file": "D:\\github\\futuapi4go\\pkg\\constant\\validation_test.go", "source_location": "L72"}, {"caller_nid": "constant_validation_test_testvalidateqty", "callee": "ValidateQty", "is_member_call": false, "source_file": "D:\\github\\futuapi4go\\pkg\\constant\\validation_test.go", "source_location": "L77"}, {"caller_nid": "constant_validation_test_testvalidateqty", "callee": "Error", "is_member_call": true, "source_file": "D:\\github\\futuapi4go\\pkg\\constant\\validation_test.go", "source_location": "L78"}, {"caller_nid": "constant_validation_test_testvalidateqty", "callee": "ValidateQty", "is_member_call": false, "source_file": "D:\\github\\futuapi4go\\pkg\\constant\\validation_test.go", "source_location": "L80"}, {"caller_nid": "constant_validation_test_testvalidateqty", "callee": "Error", "is_member_call": true, "source_file": "D:\\github\\futuapi4go\\pkg\\constant\\validation_test.go", "source_location": "L81"}, {"caller_nid": "constant_validation_test_testvalidateqty", "callee": "ValidateQty", "is_member_call": false, "source_file": "D:\\github\\futuapi4go\\pkg\\constant\\validation_test.go", "source_location": "L83"}, {"caller_nid": "constant_validation_test_testvalidateqty", "callee": "Errorf", "is_member_call": true, "source_file": "D:\\github\\futuapi4go\\pkg\\constant\\validation_test.go", "source_location": "L84"}, {"caller_nid": "constant_validation_test_testvalidateqty", "callee": "ValidateQty", "is_member_call": false, "source_file": "D:\\github\\futuapi4go\\pkg\\constant\\validation_test.go", "source_location": "L86"}, {"caller_nid": "constant_validation_test_testvalidateqty", "callee": "Error", "is_member_call": true, "source_file": "D:\\github\\futuapi4go\\pkg\\constant\\validation_test.go", "source_location": "L87"}, {"caller_nid": "constant_validation_test_testvalidateprice", "callee": "ValidatePrice", "is_member_call": false, "source_file": "D:\\github\\futuapi4go\\pkg\\constant\\validation_test.go", "source_location": "L92"}, {"caller_nid": "constant_validation_test_testvalidateprice", "callee": "Error", "is_member_call": true, "source_file": "D:\\github\\futuapi4go\\pkg\\constant\\validation_test.go", "source_location": "L93"}, {"caller_nid": "constant_validation_test_testvalidateprice", "callee": "ValidatePrice", "is_member_call": false, "source_file": "D:\\github\\futuapi4go\\pkg\\constant\\validation_test.go", "source_location": "L95"}, {"caller_nid": "constant_validation_test_testvalidateprice", "callee": "Errorf", "is_member_call": true, "source_file": "D:\\github\\futuapi4go\\pkg\\constant\\validation_test.go", "source_location": "L96"}, {"caller_nid": "constant_validation_test_testvalidateprice", "callee": "ValidatePrice", "is_member_call": false, "source_file": "D:\\github\\futuapi4go\\pkg\\constant\\validation_test.go", "source_location": "L98"}, {"caller_nid": "constant_validation_test_testvalidateprice", "callee": "Errorf", "is_member_call": true, "source_file": "D:\\github\\futuapi4go\\pkg\\constant\\validation_test.go", "source_location": "L99"}, {"caller_nid": "constant_validation_test_testvalidateprice", "callee": "ValidatePrice", "is_member_call": false, "source_file": "D:\\github\\futuapi4go\\pkg\\constant\\validation_test.go", "source_location": "L101"}, {"caller_nid": "constant_validation_test_testvalidateprice", "callee": "Error", "is_member_call": true, "source_file": "D:\\github\\futuapi4go\\pkg\\constant\\validation_test.go", "source_location": "L102"}, {"caller_nid": "constant_validation_test_testvalidateremark", "callee": "ValidateRemark", "is_member_call": false, "source_file": "D:\\github\\futuapi4go\\pkg\\constant\\validation_test.go", "source_location": "L107"}, {"caller_nid": "constant_validation_test_testvalidateremark", "callee": "Errorf", "is_member_call": true, "source_file": "D:\\github\\futuapi4go\\pkg\\constant\\validation_test.go", "source_location": "L108"}, {"caller_nid": "constant_validation_test_testvalidateremark", "callee": "ValidateRemark", "is_member_call": false, "source_file": "D:\\github\\futuapi4go\\pkg\\constant\\validation_test.go", "source_location": "L110"}, {"caller_nid": "constant_validation_test_testvalidateremark", "callee": "Errorf", "is_member_call": true, "source_file": "D:\\github\\futuapi4go\\pkg\\constant\\validation_test.go", "source_location": "L111"}, {"caller_nid": "constant_validation_test_testvalidateremark", "callee": "string", "is_member_call": false, "source_file": "D:\\github\\futuapi4go\\pkg\\constant\\validation_test.go", "source_location": "L113"}, {"caller_nid": "constant_validation_test_testvalidateremark", "callee": "make", "is_member_call": false, "source_file": "D:\\github\\futuapi4go\\pkg\\constant\\validation_test.go", "source_location": "L113"}, {"caller_nid": "constant_validation_test_testvalidateremark", "callee": "ValidateRemark", "is_member_call": false, "source_file": "D:\\github\\futuapi4go\\pkg\\constant\\validation_test.go", "source_location": "L114"}, {"caller_nid": "constant_validation_test_testvalidateremark", "callee": "Error", "is_member_call": true, "source_file": "D:\\github\\futuapi4go\\pkg\\constant\\validation_test.go", "source_location": "L115"}]}